survey_personal_incomes/__init__.py
survey_personal_incomes/load.py
survey_personal_incomes/main.py
survey_personal_incomes/save.py
survey_personal_incomes-1.0.0.dist-info/METADATA
survey_personal_incomes-1.0.0.dist-info/WHEEL
survey_personal_incomes-1.0.0.dist-info/entry_points.txt
survey_personal_incomes-1.0.0.dist-info/top_level.txt
survey_personal_incomes-1.0.0.dist-info/RECORD
