Metadata-Version: 2.1
Name: survey-personal-incomes
Version: 1.0.0
Summary: A Python package to manage Survey of Personal Incomes microdata.
Home-page: http://github.com/nikhilwoodruff/survey_personal_incomes
Author: Nikhil Woodruff
Author-email: nikhil.woodruff@outlook.com
License: UNKNOWN
Platform: UNKNOWN
Requires-Dist: pandas
Requires-Dist: openpyxl
Requires-Dist: xlrd
